{
  "id" : "schema_selection_liver",
  "algorithm" : "eod_public",
  "version" : "1.2",
  "name" : "Schema Selection Liver",
  "title" : "Schema selection for Liver",
  "last_modified" : "2018-05-09T15:33:17.533Z",
  "definition" : [ {
    "key" : "site",
    "name" : "Primary Site",
    "type" : "INPUT"
  }, {
    "key" : "hist",
    "name" : "Histology",
    "type" : "INPUT"
  }, {
    "key" : "result",
    "name" : "Result",
    "type" : "ENDPOINT"
  } ],
  "rows" : [ [ "C220", "8000-8700, 8720-8790, 9700-9701", "MATCH" ] ]
}