{
  "id" : "schema_selection_medulloblastoma_pnet",
  "algorithm" : "pediatric",
  "version" : "1.3",
  "name" : "Schema Selection Medulloblastoma- pNET",
  "title" : "Schema selection for Medulloblastoma- pNET",
  "last_modified" : "2024-05-03T19:13:39.996Z",
  "definition" : [ {
    "key" : "site",
    "name" : "Primary Site",
    "type" : "INPUT"
  }, {
    "key" : "hist",
    "name" : "Histology",
    "type" : "INPUT"
  }, {
    "key" : "result",
    "name" : "Result",
    "type" : "ENDPOINT"
  } ],
  "rows" : [ [ "C700-C729", "9473", "MATCH" ] ]
}