{
  "id" : "path_m_hbx",
  "algorithm" : "tnm",
  "version" : "1.0",
  "name" : "Path M",
  "title" : "Pathologic M",
  "last_modified" : "2015-10-10T19:51:33.914Z",
  "definition" : [ {
    "key" : "path_m",
    "name" : "Pathological M",
    "type" : "INPUT"
  }, {
    "key" : "path_m_display",
    "name" : "Pathological M Display",
    "type" : "DESCRIPTION"
  }, {
    "key" : "description",
    "name" : "Description",
    "type" : "DESCRIPTION"
  }, {
    "key" : "notes",
    "name" : "Registrar Notes",
    "type" : "DESCRIPTION"
  } ],
  "rows" : [ [ "1", "M1", "Distant metastasis", "Superior mesenteric lymph node(s)\n\nDistant lymph node(s), NOS\n\nCarcinomatosis\n\nDistant metastasis WITH or WITHOUT distant lymph node(s) \n\nDistant metastasis, NOS\n\nStated as M1" ] ]
}