{
  "id" : "schema_selection_melanoma_larynx_supraglottic",
  "algorithm" : "tnm",
  "version" : "1.0",
  "name" : "Schema Selection MelanomaLarynxSupraglottic",
  "title" : "Schema selection for MelanomaLarynxSupraglottic",
  "last_modified" : "2015-11-23T01:04:12.046Z",
  "definition" : [ {
    "key" : "site",
    "name" : "Primary Site",
    "type" : "INPUT"
  }, {
    "key" : "hist",
    "name" : "Histology",
    "type" : "INPUT"
  }, {
    "key" : "result",
    "name" : "Result",
    "type" : "ENDPOINT"
  } ],
  "rows" : [ [ "C321", "8720-8790", "MATCH" ] ]
}