{
  "id" : "seer_mets_merkelcellscrotum_96689",
  "algorithm" : "tnm",
  "version" : "1.0",
  "name" : "SEER Mets MerkelCellScrotum",
  "title" : "SEER Mets",
  "notes" : "**Note 1:**  In-transit metastasis is coded in SEER Regional Nodes.\n\n**Note 2:**  Nodes in contiguous (secondary) and bidirectional (cephalad/caudal) primary nodal basins are coded in SEER Regional Nodes.",
  "last_modified" : "2015-11-25T20:26:34.072Z",
  "definition" : [ {
    "key" : "seer_mets",
    "name" : "Code",
    "type" : "INPUT"
  }, {
    "key" : "manual",
    "name" : "Summary Stage Manual",
    "type" : "DESCRIPTION"
  }, {
    "key" : "notes",
    "name" : "Registrar Notes",
    "type" : "DESCRIPTION"
  }, {
    "key" : "ss2017_m",
    "name" : "Summary Stage 2017 M",
    "type" : "ENDPOINT"
  } ],
  "rows" : [ [ "00", "None\n\nNo distant metastasis", "", "VALUE:NONE" ], [ "70", "Distant site(s)/lymph node(s) involved\n\n    Distant lymph node(s)\n\n    Further contiguous extension\n       Testis\n\n    Metastasis", "Underlying cartilage, bone\n\nMetastasis to skin or subcutaneous tissue\n\nCarcinomatosis\n\nDistant metastasis WITH or WITHOUT distant lymph node(s)\n\nDistant metastasis, NOS\n\nStated as M1 (M1a, M1b, M1 [NOS])", "VALUE:D" ], [ "99", "Unknown; distant metastasis not stated\nDistant metastasis cannot be assessed\nNot documented in patient record", "", "VALUE:U" ] ]
}