{
  "id" : "schema_selection_renal_tumors_nephroblastoma",
  "algorithm" : "toronto",
  "version" : "0.2",
  "name" : "Schema Selection Renal Tumors: Nephroblastoma",
  "title" : "Schema selection for Renal Tumors: Nephroblastoma",
  "last_modified" : "2022-09-15T20:45:37.007Z",
  "definition" : [ {
    "key" : "site",
    "name" : "Primary Site",
    "type" : "INPUT"
  }, {
    "key" : "hist",
    "name" : "Histology",
    "type" : "INPUT"
  }, {
    "key" : "behavior",
    "name" : "Behavior",
    "type" : "INPUT"
  }, {
    "key" : "result",
    "name" : "Result",
    "type" : "ENDPOINT"
  } ],
  "rows" : [ [ "C649, C659", "8959, 8960", "3", "MATCH" ] ]
}