{
  "id" : "lymph_nodes_size_ajcc6_table_csv1_xex",
  "algorithm" : "cs",
  "version" : "02.05.50",
  "name" : "Lymph Nodes Size AJCC 6 Table CSv1",
  "title" : "Lymph Nodes Size AJCC 6 Table CSv1",
  "notes" : "**Note**:  For OBSOLETE CS Lymph Node codes ONLY, the N category for cases coded in CSv1 is determined by the size of involved nodes coded in CS Site-Specific Factor 1, Size of Lymph Nodes, as shown in this table.",
  "last_modified" : "2015-05-27T16:19:25.835Z",
  "definition" : [ {
    "key" : "nodes",
    "name" : "CS Lymph Nodes",
    "type" : "INPUT"
  }, {
    "key" : "ssf1",
    "name" : "CS SSF1 Size of Nodes",
    "type" : "INPUT"
  }, {
    "key" : "ajcc6_n",
    "name" : "TNM 6 N",
    "type" : "ENDPOINT"
  } ],
  "rows" : [ [ "100", "000", "ERROR:" ], [ "110", "000", "ERROR:" ], [ "120", "000", "ERROR:" ], [ "200", "000", "ERROR:" ], [ "210", "000", "ERROR:" ], [ "220", "000", "ERROR:" ], [ "300", "000", "ERROR:" ], [ "310", "000", "ERROR:" ], [ "320", "000", "ERROR:" ], [ "400", "000", "ERROR:" ], [ "410", "000", "ERROR:" ], [ "420", "000", "ERROR:" ], [ "500", "000", "ERROR:" ], [ "510", "000", "ERROR:" ], [ "520", "000", "ERROR:" ], [ "100", "001-060", "VALUE:N1" ], [ "110", "001-060", "VALUE:N1" ], [ "120", "001-060", "VALUE:N1" ], [ "200", "001-060", "VALUE:N1" ], [ "210", "001-060", "VALUE:N1" ], [ "220", "001-060", "VALUE:N1" ], [ "300", "001-060", "VALUE:N1" ], [ "310", "001-060", "VALUE:N1" ], [ "320", "001-060", "VALUE:N1" ], [ "400", "001-060", "VALUE:N2" ], [ "410", "001-060", "VALUE:N2" ], [ "420", "001-060", "VALUE:N2" ], [ "500", "001-060", "VALUE:N1" ], [ "510", "001-060", "VALUE:N1" ], [ "520", "001-060", "VALUE:N1" ], [ "100", "061-980", "VALUE:N3a" ], [ "110", "061-980", "VALUE:N3a" ], [ "120", "061-980", "VALUE:N3a" ], [ "200", "061-980", "VALUE:N3a" ], [ "210", "061-980", "VALUE:N3a" ], [ "220", "061-980", "VALUE:N3a" ], [ "300", "061-980", "VALUE:N3a" ], [ "310", "061-980", "VALUE:N3a" ], [ "320", "061-980", "VALUE:N3a" ], [ "400", "061-980", "VALUE:N3a" ], [ "410", "061-980", "VALUE:N3a" ], [ "420", "061-980", "VALUE:N3a" ], [ "500", "061-980", "VALUE:N3a" ], [ "510", "061-980", "VALUE:N3a" ], [ "520", "061-980", "VALUE:N3a" ], [ "100", "981-987", "ERROR:" ], [ "110", "981-987", "ERROR:" ], [ "120", "981-987", "ERROR:" ], [ "200", "981-987", "ERROR:" ], [ "210", "981-987", "ERROR:" ], [ "220", "981-987", "ERROR:" ], [ "300", "981-987", "ERROR:" ], [ "310", "981-987", "ERROR:" ], [ "320", "981-987", "ERROR:" ], [ "400", "981-987", "ERROR:" ], [ "410", "981-987", "ERROR:" ], [ "420", "981-987", "ERROR:" ], [ "500", "981-987", "ERROR:" ], [ "510", "981-987", "ERROR:" ], [ "520", "981-987", "ERROR:" ], [ "100", "988", "ERROR:" ], [ "110", "988", "ERROR:" ], [ "120", "988", "ERROR:" ], [ "200", "988", "ERROR:" ], [ "210", "988", "ERROR:" ], [ "220", "988", "ERROR:" ], [ "300", "988", "ERROR:" ], [ "310", "988", "ERROR:" ], [ "320", "988", "ERROR:" ], [ "400", "988", "ERROR:" ], [ "410", "988", "ERROR:" ], [ "420", "988", "ERROR:" ], [ "500", "988", "ERROR:" ], [ "510", "988", "ERROR:" ], [ "520", "988", "ERROR:" ], [ "100", "989", "ERROR:" ], [ "110", "989", "ERROR:" ], [ "120", "989", "ERROR:" ], [ "200", "989", "ERROR:" ], [ "210", "989", "ERROR:" ], [ "220", "989", "ERROR:" ], [ "300", "989", "ERROR:" ], [ "310", "989", "ERROR:" ], [ "320", "989", "ERROR:" ], [ "400", "989", "ERROR:" ], [ "410", "989", "ERROR:" ], [ "420", "989", "ERROR:" ], [ "500", "989", "ERROR:" ], [ "510", "989", "ERROR:" ], [ "520", "989", "ERROR:" ], [ "100", "990-996", "VALUE:N1" ], [ "110", "990-996", "VALUE:N1" ], [ "120", "990-996", "VALUE:N1" ], [ "200", "990-996", "VALUE:N1" ], [ "210", "990-996", "VALUE:N1" ], [ "220", "990-996", "VALUE:N1" ], [ "300", "990-996", "VALUE:N1" ], [ "310", "990-996", "VALUE:N1" ], [ "320", "990-996", "VALUE:N1" ], [ "400", "990-996", "VALUE:N2" ], [ "410", "990-996", "VALUE:N2" ], [ "420", "990-996", "VALUE:N2" ], [ "500", "990-996", "VALUE:N1" ], [ "510", "990-996", "VALUE:N1" ], [ "520", "990-996", "VALUE:N1" ], [ "100", "997", "VALUE:N3a" ], [ "110", "997", "VALUE:N3a" ], [ "120", "997", "VALUE:N3a" ], [ "200", "997", "VALUE:N3a" ], [ "210", "997", "VALUE:N3a" ], [ "220", "997", "VALUE:N3a" ], [ "300", "997", "VALUE:N3a" ], [ "310", "997", "VALUE:N3a" ], [ "320", "997", "VALUE:N3a" ], [ "400", "997", "VALUE:N3a" ], [ "410", "997", "VALUE:N3a" ], [ "420", "997", "VALUE:N3a" ], [ "500", "997", "VALUE:N3a" ], [ "510", "997", "VALUE:N3a" ], [ "520", "997", "VALUE:N3a" ], [ "100", "999", "VALUE:N1" ], [ "110", "999", "VALUE:N1" ], [ "120", "999", "VALUE:N1" ], [ "200", "999", "VALUE:N1" ], [ "210", "999", "VALUE:N1" ], [ "220", "999", "VALUE:N1" ], [ "300", "999", "VALUE:N1" ], [ "310", "999", "VALUE:N1" ], [ "320", "999", "VALUE:N1" ], [ "400", "999", "VALUE:N2" ], [ "410", "999", "VALUE:N2" ], [ "420", "999", "VALUE:N2" ], [ "500", "999", "VALUE:N1" ], [ "510", "999", "VALUE:N1" ], [ "520", "999", "VALUE:N1" ] ]
}