{
  "id" : "ssf7_sbv",
  "algorithm" : "tnm",
  "version" : "1.8",
  "name" : "SSF7",
  "title" : "Site-Specific Factor 7",
  "subtitle" : "Mucoepidermoid Carcinoma - Grade",
  "notes" : "**Note 1:**  Code only for cases diagnosed as mucoepidermoid carcinoma, histology code 8430/3.  \n\n**Note 2:**  Use code 987 for all other histologies.  Use code 998 if no pathologic examination of primary site.  Use code 999 if grade not stated on pathologic examination.",
  "last_modified" : "2018-05-02T20:27:52.590Z",
  "definition" : [ {
    "key" : "ssf7",
    "name" : "Code",
    "type" : "INPUT"
  }, {
    "key" : "description",
    "name" : "Description",
    "type" : "DESCRIPTION"
  } ],
  "rows" : [ [ "010", "Low grade" ], [ "020", "High grade" ], [ "987", "Not applicable:  Histology not mucoepidermoid carcinoma" ], [ "988", "Not applicable: Information not collected for this case\n(If this information is required by your standard setter, use of code 988 may result in an edit error.)" ], [ "998", "No pathologic examination of primary site" ], [ "999", "Unknown or no information\nNot documented in patient record" ] ]
}